AUTHORS.rst
CONTRIBUTING.rst
HISTORY.rst
MANIFEST.in
README.rst
setup.cfg
setup.py
docs/Makefile
docs/authors.rst
docs/conf.py
docs/contributing.rst
docs/history.rst
docs/index.rst
docs/installation.rst
docs/make.bat
docs/readme.rst
docs/usage.rst
dupes/__init__.py
dupes/dupes.py
dupes.egg-info/PKG-INFO
dupes.egg-info/SOURCES.txt
dupes.egg-info/dependency_links.txt
dupes.egg-info/not-zip-safe
dupes.egg-info/requires.txt
dupes.egg-info/top_level.txt
scripts/dupes
tests/__init__.py
tests/test_dupes.py