Metadata-Version: 1.1
Name: dupes
Version: 0.1.0
Summary: Identify duplicate files (by SHA1) and remove them if needed
Home-page: https://github.com/dwwkelly/dupes
Author: Devin Kelly
Author-email: dwwkelly@fastmail.fm
License: GPL2
Keywords: dupes
Platform: UNKNOWN
Classifier: Development Status :: 2 - Pre-Alpha
Classifier: Intended Audience :: Developers
Classifier: License :: OSI Approved :: GPL2 License
Classifier: Natural Language :: English
Classifier: Programming Language :: Python :: 2
Classifier: Programming Language :: Python :: 2.6
Classifier: Programming Language :: Python :: 2.7
Classifier: Programming Language :: Python :: 3
Classifier: Programming Language :: Python :: 3.3
Classifier: Programming Language :: Python :: 3.4
